edx_opaque_keys-3.0.0.dist-info/licenses/AUTHORS
edx_opaque_keys-3.0.0.dist-info/licenses/LICENSE
opaque_keys/__init__.py
opaque_keys/py.typed
opaque_keys/edx/__init__.py
opaque_keys/edx/asides.py
opaque_keys/edx/block_types.py
opaque_keys/edx/keys.py
opaque_keys/edx/locations.py
opaque_keys/edx/locator.py
opaque_keys/edx/django/__init__.py
opaque_keys/edx/django/models.py
opaque_keys/edx/django/tests/__init__.py
opaque_keys/edx/django/tests/models.py
opaque_keys/edx/django/tests/test_models.py
opaque_keys/edx/tests/__init__.py
opaque_keys/edx/tests/test_aside_keys.py
opaque_keys/edx/tests/test_asset_locators.py
opaque_keys/edx/tests/test_block_types.py
opaque_keys/edx/tests/test_block_usage_locators.py
opaque_keys/edx/tests/test_collection_locators.py
opaque_keys/edx/tests/test_container_locators.py
opaque_keys/edx/tests/test_course_locators.py
opaque_keys/edx/tests/test_default_deprecated.py
opaque_keys/edx/tests/test_deprecated_locations.py
opaque_keys/edx/tests/test_is_course.py
opaque_keys/edx/tests/test_library_locators.py
opaque_keys/edx/tests/test_library_usage_locators.py
opaque_keys/edx/tests/test_locators.py
opaque_keys/edx/tests/test_properties.py
opaque_keys/tests/__init__.py
opaque_keys/tests/strategies.py
opaque_keys/tests/test_opaque_keys.py
settings/__init__.py
settings/base.py
settings/test.py
edx_opaque_keys-3.0.0.dist-info/METADATA
edx_opaque_keys-3.0.0.dist-info/WHEEL
edx_opaque_keys-3.0.0.dist-info/entry_points.txt
edx_opaque_keys-3.0.0.dist-info/top_level.txt
edx_opaque_keys-3.0.0.dist-info/RECORD
