Metadata-Version: 2.4
Name: edx-opaque-keys
Version: 3.0.0
Home-page: https://github.com/openedx/opaque-keys
Author: edX
License: AGPL-3.0
Classifier: Intended Audience :: Developers
Classifier: License :: OSI Approved :: GNU Affero General Public License v3
Classifier: Operating System :: OS Independent
Classifier: Programming Language :: Python :: 3
Classifier: Programming Language :: Python :: 3.11
Classifier: Programming Language :: Python :: 3.12
Classifier: Framework :: Django
Classifier: Framework :: Django :: 4.2
License-File: LICENSE
License-File: AUTHORS
Requires-Dist: pymongo
Requires-Dist: stevedore>=0.14.1
Requires-Dist: typing-extensions
Provides-Extra: django
Dynamic: author
Dynamic: classifier
Dynamic: description
Dynamic: description-content-type
Dynamic: home-page
Dynamic: license
Dynamic: license-file
Dynamic: provides-extra
Dynamic: requires-dist
